air_quotes/__init__.py
air_quotes/sarcasm.py
air_quotes-0.1.3.dist-info/WHEEL
air_quotes-0.1.3.dist-info/METADATA
air_quotes-0.1.3.dist-info/RECORD
