Metadata-Version: 2.1
Name: air-quotes
Version: 0.1.3
Summary: Mock any proposal, reasonable or otherwise
Author: JB
Author-email: jb.tellez@gmail.com
Requires-Python: >=3.7,<4.0
Classifier: Programming Language :: Python :: 3
Classifier: Programming Language :: Python :: 3.7
Classifier: Programming Language :: Python :: 3.8
